Metadata-Version: 2.1
Name: superftp
Version: 1.0.3
Summary: Multisegment FTP Client
Home-page: https://github.com/Snackman8/superftp
License: License :: OSI Approved :: Apache Software License 2.0 (Apache-2.0)
Platform: UNKNOWN
Requires-Python: >=2.7
